{"Enterprise Risk Management": {"name": "Enterprise Risk Management", "path": "All Knowledge > Applied Sciences > Business > Finance > Financial Regulation > Compliance and Risk Management > Risk Management Frameworks"}, "Operational Risk Management": {"name": "Operational Risk Management", "path": "All Knowledge > Applied Sciences > Business > Finance > Financial Regulation > Compliance and Risk Management > Risk Management Frameworks"}, "name": "Risk Management Frameworks", "path": "All Knowledge > Applied Sciences > Business > Finance > Financial Regulation > Compliance and Risk Management"}