{"Teaching Methods": {"Suzuki Method": {"name": "Suzuki Method", "path": "All Knowledge > Humanities > Art > Music > Music Education > Teaching Methods"}, "Kod_ly Method": {"name": "Kod_ly Method", "path": "All Knowledge > Humanities > Art > Music > Music Education > Teaching Methods"}, "Orff Schulwerk": {"name": "Orff Schulwerk", "path": "All Knowledge > Humanities > Art > Music > Music Education > Teaching Methods"}, "Dalcroze Eurhythmics": {"name": "Dalcroze Eurhythmics", "path": "All Knowledge > Humanities > Art > Music > Music Education > Teaching Methods"}, "name": "Teaching Methods", "path": "All Knowledge > Humanities > Art > Music > Music Education"}, "Music Theory Pedagogy": {"name": "Music Theory Pedagogy", "path": "All Knowledge > Humanities > Art > Music > Music Education"}, "Music History Pedagogy": {"name": "Music History Pedagogy", "path": "All Knowledge > Humanities > Art > Music > Music Education"}, "Instrumental and Vocal Pedagogy": {"name": "Instrumental and Vocal Pedagogy", "path": "All Knowledge > Humanities > Art > Music > Music Education"}, "name": "Music Education", "path": "All Knowledge > Humanities > Art > Music"}