{"Interest Rates": {"name": "Interest Rates", "path": "All Knowledge > Social Sciences > Economics > Microeconomics > Factor Markets > Capital Market"}, "Investment": {"name": "Investment", "path": "All Knowledge > Social Sciences > Economics > Microeconomics > Factor Markets > Capital Market"}, "Capital Accumulation": {"name": "Capital Accumulation", "path": "All Knowledge > Social Sciences > Economics > Microeconomics > Factor Markets > Capital Market"}, "name": "Capital Market", "path": "All Knowledge > Social Sciences > Economics > Microeconomics > Factor Markets"}