{"Physical Sciences": {"Physics": {"name": "Physics", "path": "All Knowledge > Science > Physical Sciences"}, "Chemistry": {"name": "Chemistry", "path": "All Knowledge > Science > Physical Sciences"}, "Astronomy": {"name": "Astronomy", "path": "All Knowledge > Science > Physical Sciences"}, "Earth Science": {"name": "Earth Science", "path": "All Knowledge > Science > Physical Sciences"}, "name": "Physical Sciences", "path": "All Knowledge > Science"}, "Life Sciences": {"Biology": {"name": "Biology", "path": "All Knowledge > Science > Life Sciences"}, "Ecology": {"name": "Ecology", "path": "All Knowledge > Science > Life Sciences"}, "Genetics": {"name": "Genetics", "path": "All Knowledge > Science > Life Sciences"}, "Zoology": {"name": "Zoology", "path": "All Knowledge > Science > Life Sciences"}, "Botany": {"name": "Botany", "path": "All Knowledge > Science > Life Sciences"}, "name": "Life Sciences", "path": "All Knowledge > Science"}, "Social Sciences": {"Anthropology": {"name": "Anthropology", "path": "All Knowledge > Science > Social Sciences"}, "Economics": {"name": "Economics", "path": "All Knowledge > Science > Social Sciences"}, "Political Science": {"name": "Political Science", "path": "All Knowledge > Science > Social Sciences"}, "Psychology": {"name": "Psychology", "path": "All Knowledge > Science > Social Sciences"}, "Sociology": {"name": "Sociology", "path": "All Knowledge > Science > Social Sciences"}, "name": "Social Sciences", "path": "All Knowledge > Science"}, "name": "Science", "path": "All Knowledge"}