{"Brain Structure and Function": {"Neuroanatomy": {"Brain Regions": {"name": "Brain Regions", "path": "All Knowledge > Social Sciences > Psychology > Neuropsychology > Brain Structure and Function > Neuroanatomy"}, "Neural Pathways": {"name": "Neural Pathways", "path": "All Knowledge > Social Sciences > Psychology > Neuropsychology > Brain Structure and Function > Neuroanatomy"}, "Neurotransmitters": {"name": "Neurotransmitters", "path": "All Knowledge > Social Sciences > Psychology > Neuropsychology > Brain Structure and Function > Neuroanatomy"}, "name": "Neuroanatomy", "path": "All Knowledge > Social Sciences > Psychology > Neuropsychology > Brain Structure and Function"}, "Neurophysiology": {"Neuronal Communication": {"name": "Neuronal Communication", "path": "All Knowledge > Social Sciences > Psychology > Neuropsychology > Brain Structure and Function > Neurophysiology"}, "Synaptic Plasticity": {"name": "Synaptic Plasticity", "path": "All Knowledge > Social Sciences > Psychology > Neuropsychology > Brain Structure and Function > Neurophysiology"}, "Neural Networks": {"name": "Neural Networks", "path": "All Knowledge > Social Sciences > Psychology > Neuropsychology > Brain Structure and Function > Neurophysiology"}, "name": "Neurophysiology", "path": "All Knowledge > Social Sciences > Psychology > Neuropsychology > Brain Structure and Function"}, "name": "Brain Structure and Function", "path": "All Knowledge > Social Sciences > Psychology > Neuropsychology"}, "Cognitive Neuropsychology": {"Perception": {"Visual Perception": {"name": "Visual Perception", "path": "All Knowledge > Social Sciences > Psychology > Neuropsychology > Cognitive Neuropsychology > Perception"}, "Auditory Perception": {"name": "Auditory Perception", "path": "All Knowledge > Social Sciences > Psychology > Neuropsychology > Cognitive Neuropsychology > Perception"}, "Olfactory Perception": {"name": "Olfactory Perception", "path": "All Knowledge > Social Sciences > Psychology > Neuropsychology > Cognitive Neuropsychology > Perception"}, "Gustatory Perception": {"name": "Gustatory Perception", "path": "All Knowledge > Social Sciences > Psychology > Neuropsychology > Cognitive Neuropsychology > Perception"}, "Tactile Perception": {"name": "Tactile Perception", "path": "All Knowledge > Social Sciences > Psychology > Neuropsychology > Cognitive Neuropsychology > Perception"}, "name": "Perception", "path": "All Knowledge > Social Sciences > Psychology > Neuropsychology > Cognitive Neuropsychology"}, "Attention": {"Selective Attention": {"name": "Selective Attention", "path": "All Knowledge > Social Sciences > Psychology > Neuropsychology > Cognitive Neuropsychology > Attention"}, "Divided Attention": {"name": "Divided Attention", "path": "All Knowledge > Social Sciences > Psychology > Neuropsychology > Cognitive Neuropsychology > Attention"}, "Sustained Attention": {"name": "Sustained Attention", "path": "All Knowledge > Social Sciences > Psychology > Neuropsychology > Cognitive Neuropsychology > Attention"}, "name": "Attention", "path": "All Knowledge > Social Sciences > Psychology > Neuropsychology > Cognitive Neuropsychology"}, "Memory": {"Short_term Memory": {"name": "Short_term Memory", "path": "All Knowledge > Social Sciences > Psychology > Neuropsychology > Cognitive Neuropsychology > Memory"}, "Long_term Memory": {"name": "Long_term Memory", "path": "All Knowledge > Social Sciences > Psychology > Neuropsychology > Cognitive Neuropsychology > Memory"}, "Working Memory": {"name": "Working Memory", "path": "All Knowledge > Social Sciences > Psychology > Neuropsychology > Cognitive Neuropsychology > Memory"}, "Memory Consolidation": {"name": "Memory Consolidation", "path": "All Knowledge > Social Sciences > Psychology > Neuropsychology > Cognitive Neuropsychology > Memory"}, "name": "Memory", "path": "All Knowledge > Social Sciences > Psychology > Neuropsychology > Cognitive Neuropsychology"}, "Language": {"Language Processing": {"name": "Language Processing", "path": "All Knowledge > Social Sciences > Psychology > Neuropsychology > Cognitive Neuropsychology > Language"}, "Language Production": {"name": "Language Production", "path": "All Knowledge > Social Sciences > Psychology > Neuropsychology > Cognitive Neuropsychology > Language"}, "Language Comprehension": {"name": "Language Comprehension", "path": "All Knowledge > Social Sciences > Psychology > Neuropsychology > Cognitive Neuropsychology > Language"}, "name": "Language", "path": "All Knowledge > Social Sciences > Psychology > Neuropsychology > Cognitive Neuropsychology"}, "Executive Functions": {"Decision Making": {"name": "Decision Making", "path": "All Knowledge > Social Sciences > Psychology > Neuropsychology > Cognitive Neuropsychology > Executive Functions"}, "Problem Solving": {"name": "Problem Solving", "path": "All Knowledge > Social Sciences > Psychology > Neuropsychology > Cognitive Neuropsychology > Executive Functions"}, "Cognitive Flexibility": {"name": "Cognitive Flexibility", "path": "All Knowledge > Social Sciences > Psychology > Neuropsychology > Cognitive Neuropsychology > Executive Functions"}, "Inhibition": {"name": "Inhibition", "path": "All Knowledge > Social Sciences > Psychology > Neuropsychology > Cognitive Neuropsychology > Executive Functions"}, "name": "Executive Functions", "path": "All Knowledge > Social Sciences > Psychology > Neuropsychology > Cognitive Neuropsychology"}, "name": "Cognitive Neuropsychology", "path": "All Knowledge > Social Sciences > Psychology > Neuropsychology"}, "Affective Neuropsychology": {"Emotions": {"Emotional Processing": {"name": "Emotional Processing", "path": "All Knowledge > Social Sciences > Psychology > Neuropsychology > Affective Neuropsychology > Emotions"}, "Emotional Regulation": {"name": "Emotional Regulation", "path": "All Knowledge > Social Sciences > Psychology > Neuropsychology > Affective Neuropsychology > Emotions"}, "Emotional Expression": {"name": "Emotional Expression", "path": "All Knowledge > Social Sciences > Psychology > Neuropsychology > Affective Neuropsychology > Emotions"}, "name": "Emotions", "path": "All Knowledge > Social Sciences > Psychology > Neuropsychology > Affective Neuropsychology"}, "Motivation": {"Reward Systems": {"name": "Reward Systems", "path": "All Knowledge > Social Sciences > Psychology > Neuropsychology > Affective Neuropsychology > Motivation"}, "Goal_directed Behavior": {"name": "Goal_directed Behavior", "path": "All Knowledge > Social Sciences > Psychology > Neuropsychology > Affective Neuropsychology > Motivation"}, "Intrinsic and Extrinsic Motivation": {"name": "Intrinsic and Extrinsic Motivation", "path": "All Knowledge > Social Sciences > Psychology > Neuropsychology > Affective Neuropsychology > Motivation"}, "name": "Motivation", "path": "All Knowledge > Social Sciences > Psychology > Neuropsychology > Affective Neuropsychology"}, "name": "Affective Neuropsychology", "path": "All Knowledge > Social Sciences > Psychology > Neuropsychology"}, "Social Neuropsychology": {"Social Cognition": {"Theory of Mind": {"name": "Theory of Mind", "path": "All Knowledge > Social Sciences > Psychology > Neuropsychology > Social Neuropsychology > Social Cognition"}, "Empathy": {"name": "Empathy", "path": "All Knowledge > Social Sciences > Psychology > Neuropsychology > Social Neuropsychology > Social Cognition"}, "": {"name": "", "path": "All Knowledge > Social Sciences > Psychology > Neuropsychology > Social Neuropsychology > Social Cognition"}, "name": "Social Cognition", "path": "All Knowledge > Social Sciences > Psychology > Neuropsychology > Social Neuropsychology"}, "name": "Social Neuropsychology", "path": "All Knowledge > Social Sciences > Psychology > Neuropsychology"}, "name": "Neuropsychology", "path": "All Knowledge > Social Sciences > Psychology"}