{"Accommodation": {"Hotels": {"name": "Hotels", "path": "All Knowledge > Social Sciences > Tourism > Tourism Industry > Accommodation"}, "Resorts": {"name": "Resorts", "path": "All Knowledge > Social Sciences > Tourism > Tourism Industry > Accommodation"}, "Hostels": {"name": "Hostels", "path": "All Knowledge > Social Sciences > Tourism > Tourism Industry > Accommodation"}, "Vacation Rentals": {"name": "Vacation Rentals", "path": "All Knowledge > Social Sciences > Tourism > Tourism Industry > Accommodation"}, "Camping and Caravanning": {"name": "Camping and Caravanning", "path": "All Knowledge > Social Sciences > Tourism > Tourism Industry > Accommodation"}, "name": "Accommodation", "path": "All Knowledge > Social Sciences > Tourism > Tourism Industry"}, "Transportation": {"Air Travel": {"name": "Air Travel", "path": "All Knowledge > Social Sciences > Tourism > Tourism Industry > Transportation"}, "Rail Travel": {"name": "Rail Travel", "path": "All Knowledge > Social Sciences > Tourism > Tourism Industry > Transportation"}, "Road Travel": {"name": "Road Travel", "path": "All Knowledge > Social Sciences > Tourism > Tourism Industry > Transportation"}, "Cruise Travel": {"name": "Cruise Travel", "path": "All Knowledge > Social Sciences > Tourism > Tourism Industry > Transportation"}, "name": "Transportation", "path": "All Knowledge > Social Sciences > Tourism > Tourism Industry"}, "Travel Services": {"Travel Agencies": {"name": "Travel Agencies", "path": "All Knowledge > Social Sciences > Tourism > Tourism Industry > Travel Services"}, "Tour Operators": {"name": "Tour Operators", "path": "All Knowledge > Social Sciences > Tourism > Tourism Industry > Travel Services"}, "Online Travel Platforms": {"name": "Online Travel Platforms", "path": "All Knowledge > Social Sciences > Tourism > Tourism Industry > Travel Services"}, "name": "Travel Services", "path": "All Knowledge > Social Sciences > Tourism > Tourism Industry"}, "Attractions": {"Natural Attractions": {"name": "Natural Attractions", "path": "All Knowledge > Social Sciences > Tourism > Tourism Industry > Attractions"}, "Cultural Attractions": {"name": "Cultural Attractions", "path": "All Knowledge > Social Sciences > Tourism > Tourism Industry > Attractions"}, "Theme Parks": {"name": "Theme Parks", "path": "All Knowledge > Social Sciences > Tourism > Tourism Industry > Attractions"}, "Museums and Galleries": {"name": "Museums and Galleries", "path": "All Knowledge > Social Sciences > Tourism > Tourism Industry > Attractions"}, "name": "Attractions", "path": "All Knowledge > Social Sciences > Tourism > Tourism Industry"}, "Food and Beverage": {"Restaurants": {"name": "Restaurants", "path": "All Knowledge > Social Sciences > Tourism > Tourism Industry > Food and Beverage"}, "Cafes and Bars": {"name": "Cafes and Bars", "path": "All Knowledge > Social Sciences > Tourism > Tourism Industry > Food and Beverage"}, "Street Food and Food Markets": {"name": "Street Food and Food Markets", "path": "All Knowledge > Social Sciences > Tourism > Tourism Industry > Food and Beverage"}, "name": "Food and Beverage", "path": "All Knowledge > Social Sciences > Tourism > Tourism Industry"}, "name": "Tourism Industry", "path": "All Knowledge > Social Sciences > Tourism"}