{"Distributed Ledger Technology": {"name": "Distributed Ledger Technology", "path": "All Knowledge > Applied Sciences > Business > Finance > Financial Regulation > Financial Innovation and Regulation > Financial Market Infrastructure Innovation"}, "Central Bank Digital Currencies": {"name": "Central Bank Digital Currencies", "path": "All Knowledge > Applied Sciences > Business > Finance > Financial Regulation > Financial Innovation and Regulation > Financial Market Infrastructure Innovation"}, "name": "Financial Market Infrastructure Innovation", "path": "All Knowledge > Applied Sciences > Business > Finance > Financial Regulation > Financial Innovation and Regulation"}