{"Employee Surveys": {"name": "Employee Surveys", "path": "All Knowledge > Applied Sciences > Business > Human Resources > Employee Relations > Employee Engagement"}, "Recognition Programs": {"name": "Recognition Programs", "path": "All Knowledge > Applied Sciences > Business > Human Resources > Employee Relations > Employee Engagement"}, "Team Building Activities": {"name": "Team Building Activities", "path": "All Knowledge > Applied Sciences > Business > Human Resources > Employee Relations > Employee Engagement"}, "name": "Employee Engagement", "path": "All Knowledge > Applied Sciences > Business > Human Resources > Employee Relations"}