{"Internal Energy": {"name": "Internal Energy", "path": "All Knowledge > Natural Sciences > Physics > Thermodynamics > Thermodynamic Potentials"}, "Helmholtz Free Energy": {"name": "Helmholtz Free Energy", "path": "All Knowledge > Natural Sciences > Physics > Thermodynamics > Thermodynamic Potentials"}, "Gibbs Free Energy": {"name": "Gibbs Free Energy", "path": "All Knowledge > Natural Sciences > Physics > Thermodynamics > Thermodynamic Potentials"}, "Grand Potential": {"name": "Grand Potential", "path": "All Knowledge > Natural Sciences > Physics > Thermodynamics > Thermodynamic Potentials"}, "name": "Thermodynamic Potentials", "path": "All Knowledge > Natural Sciences > Physics > Thermodynamics"}