{"China": {"name": "China", "path": "All Knowledge > Interdisciplinary Studies > Area Studies > Regional Studies > Asian Studies > East Asia"}, "Japan": {"name": "Japan", "path": "All Knowledge > Interdisciplinary Studies > Area Studies > Regional Studies > Asian Studies > East Asia"}, "Korea": {"name": "Korea", "path": "All Knowledge > Interdisciplinary Studies > Area Studies > Regional Studies > Asian Studies > East Asia"}, "name": "East Asia", "path": "All Knowledge > Interdisciplinary Studies > Area Studies > Regional Studies > Asian Studies"}