{"Planting Techniques": {"name": "Planting Techniques", "path": "All Knowledge > Applied Sciences > Agriculture > Horticulture > Crop Production > Crop Cultivation"}, "Irrigation": {"name": "Irrigation", "path": "All Knowledge > Applied Sciences > Agriculture > Horticulture > Crop Production > Crop Cultivation"}, "Weed Control": {"name": "Weed Control", "path": "All Knowledge > Applied Sciences > Agriculture > Horticulture > Crop Production > Crop Cultivation"}, "Pest Management": {"name": "Pest Management", "path": "All Knowledge > Applied Sciences > Agriculture > Horticulture > Crop Production > Crop Cultivation"}, "name": "Crop Cultivation", "path": "All Knowledge > Applied Sciences > Agriculture > Horticulture > Crop Production"}