{"Segregation of Duties": {"name": "Segregation of Duties", "path": "All Knowledge > Applied Sciences > Business > Accounting > Accounting Information Systems > Internal Controls"}, "Authorization and Approval": {"name": "Authorization and Approval", "path": "All Knowledge > Applied Sciences > Business > Accounting > Accounting Information Systems > Internal Controls"}, "Reconciliation and Review": {"name": "Reconciliation and Review", "path": "All Knowledge > Applied Sciences > Business > Accounting > Accounting Information Systems > Internal Controls"}, "name": "Internal Controls", "path": "All Knowledge > Applied Sciences > Business > Accounting > Accounting Information Systems"}