{"Visual Perception": {"name": "Visual Perception", "path": "All Knowledge > Interdisciplinary Studies > Cognitive Science > Cognitive Processes > Perception"}, "Auditory Perception": {"name": "Auditory Perception", "path": "All Knowledge > Interdisciplinary Studies > Cognitive Science > Cognitive Processes > Perception"}, "Olfactory Perception": {"name": "Olfactory Perception", "path": "All Knowledge > Interdisciplinary Studies > Cognitive Science > Cognitive Processes > Perception"}, "Gustatory Perception": {"name": "Gustatory Perception", "path": "All Knowledge > Interdisciplinary Studies > Cognitive Science > Cognitive Processes > Perception"}, "Tactile Perception": {"name": "Tactile Perception", "path": "All Knowledge > Interdisciplinary Studies > Cognitive Science > Cognitive Processes > Perception"}, "name": "Perception", "path": "All Knowledge > Interdisciplinary Studies > Cognitive Science > Cognitive Processes"}