{"Expansionary Fiscal Policy": {"name": "Expansionary Fiscal Policy", "path": "All Knowledge > Social Sciences > Economics > Public Finance > Public Expenditure > Fiscal Policy"}, "Contractionary Fiscal Policy": {"name": "Contractionary Fiscal Policy", "path": "All Knowledge > Social Sciences > Economics > Public Finance > Public Expenditure > Fiscal Policy"}, "Automatic Stabilizers": {"name": "Automatic Stabilizers", "path": "All Knowledge > Social Sciences > Economics > Public Finance > Public Expenditure > Fiscal Policy"}, "Discretionary Fiscal Policy": {"name": "Discretionary Fiscal Policy", "path": "All Knowledge > Social Sciences > Economics > Public Finance > Public Expenditure > Fiscal Policy"}, "name": "Fiscal Policy", "path": "All Knowledge > Social Sciences > Economics > Public Finance > Public Expenditure"}