{"Phases of Transformative Learning": {"name": "Phases of Transformative Learning", "path": "All Knowledge > Applied Sciences > Education > Adult Education > Adult Learning Theories > Transformative Learning"}, "Critiques of Transformative Learning": {"name": "Critiques of Transformative Learning", "path": "All Knowledge > Applied Sciences > Education > Adult Education > Adult Learning Theories > Transformative Learning"}, "name": "Transformative Learning", "path": "All Knowledge > Applied Sciences > Education > Adult Education > Adult Learning Theories"}